QuICT_sim/__init__.py
QuICT_sim/cpu_simulator/__init__.py
QuICT_sim/cpu_simulator/cpu.py
QuICT_sim/cpu_simulator/sim_back_bind.cp38-win_amd64.pyd
QuICT_sim/cpu_simulator/sim_back_bind.cp38-win_amd64.pyd.manifest
QuICT_sim/multi_nodes/__init__.py
QuICT_sim/multi_nodes/controller.py
QuICT_sim/multi_nodes/data_switch.py
QuICT_sim/multi_nodes/multi_nodes_simulator.py
QuICT_sim/multi_nodes/transpile.py
QuICT_sim/operator/__init__.py
QuICT_sim/operator/data_switch.py
QuICT_sim/operator/device_trigger.py
QuICT_sim/operator/special.py
QuICT_sim/optimization/__init__.py
QuICT_sim/optimization/optimizer.py
QuICT_sim/proxy/__init__.py
QuICT_sim/proxy/proxy.py
QuICT_sim/proxy/proxy_unit_test.py
QuICT_sim/proxy/timeout.py
quict_sim-1.0.0.dist-info/METADATA
quict_sim-1.0.0.dist-info/WHEEL
quict_sim-1.0.0.dist-info/top_level.txt
quict_sim-1.0.0.dist-info/RECORD
