Metadata-Version: 2.1
Name: quict-sim
Version: 1.0.0
Summary: High performance Quantum Circuit Simulation designed for QuICT.
Home-page: https://edu.gitee.com/quictucas/repos/quictucas/quict-sim
Author: Library for Quantum Computation and Theoretical Computer Science, ICT, CAS
Author-email: quact@ict.ac.cn
License: Apache License 2.0
Platform: Windows
Platform: Linux
Requires-Python: >=3.8
Requires-Dist: QuICT (>=0.9.9)
Requires-Dist: numpy (>=1.23.4)
Requires-Dist: scipy (>=1.9.2)
